experiment/__init__.py
experiment/cli.py
experiment/experiment.py
experiment/suites.py
experiment/tasks.py
pysurfex_experiment-0.0.1a2.data/scripts/ECF_kill_exp
pysurfex_experiment-0.0.1a2.data/scripts/ECF_status_exp
pysurfex_experiment-0.0.1a2.data/scripts/ECF_submit_exp
pysurfex_experiment-0.0.1a2.data/scripts/PySurfex
pysurfex_experiment-0.0.1a2.dist-info/METADATA
pysurfex_experiment-0.0.1a2.dist-info/WHEEL
pysurfex_experiment-0.0.1a2.dist-info/top_level.txt
pysurfex_experiment-0.0.1a2.dist-info/RECORD
