Metadata-Version: 2.1
Name: pysurfex-experiment
Version: 0.0.1a2
Summary: Pysurfex experiment
Home-page: https://github.com/metno/pysurfex-experiment
Author: Trygve Aspelien
Author-email: trygve.aspelien@met.no
License: BSD-3
Keywords: meteorology weather prediction scheduler ecflow
Platform: UNKNOWN
Classifier: Development Status :: 4 - Beta
Classifier: Intended Audience :: Science/Research
Classifier: Topic :: Scientific/Engineering :: Atmospheric Science
Classifier: Topic :: Scientific/Engineering :: Information Analysis
Classifier: License :: OSI Approved :: BSD License
Classifier: Programming Language :: Python :: 3.5
Classifier: Programming Language :: Python :: 3.6
Classifier: Programming Language :: Python :: 3.7
Requires-Dist: pysurfex
Requires-Dist: pysurfex-scheduler
Requires-Dist: toml
Requires-Dist: tomlkit
Requires-Dist: datetime
Requires-Dist: json ; python_version < "3"
Provides-Extra: test
Requires-Dist: coverage ; extra == 'test'
Requires-Dist: coveralls ; extra == 'test'
Requires-Dist: pep8 ; extra == 'test'
Requires-Dist: nose ; extra == 'test'
Requires-Dist: nose-timer ; extra == 'test'
